src/Lamel_window/AnalyzingDataSliceWin.py
src/Lamel_window/SaveResultsWin.py
src/Lamel_window/SettingsWin.py
src/Lamel_window/__init__.py
src/Lamel_window/analyzing_data_slice_win_design.py
src/Lamel_window/global_data.py
src/Lamel_window/main.py
src/Lamel_window/proccesing.py
src/Lamel_window/save_results_win_design.py
src/Lamel_window/settings_win_design.py
Lamelgraph-1.1.4.dist-info/METADATA
Lamelgraph-1.1.4.dist-info/WHEEL
Lamelgraph-1.1.4.dist-info/top_level.txt
Lamelgraph-1.1.4.dist-info/RECORD
